LICENSE.txt
setup.cfg
setup.py
gapi/__init__.py
gapi/api.py
gapi/results.py
gapi.egg-info/PKG-INFO
gapi.egg-info/SOURCES.txt
gapi.egg-info/dependency_links.txt
gapi.egg-info/requires.txt
gapi.egg-info/top_level.txt
tools/gnip_filter_analysis.py
tools/gnip_search.py
tools/gnip_time_series.py